[
  {
    "firstName": "Max",
    "lastName": "Verstappen",
    "url": "/en/drivers/max-verstappen.html",
    "team": "Red Bull Racing",
    "points": "400",
    "rank": "1"
  },
  {
    "firstName": "Sergio",
    "lastName": "Perez",
    "url": "/en/drivers/sergio-perez.html",
    "team": "Red Bull Racing",
    "points": "223",
    "rank": "2"
  },
  {
    "firstName": "Lewis",
    "lastName": "Hamilton",
    "url": "/en/drivers/lewis-hamilton.html",
    "team": "Mercedes",
    "points": "190",
    "rank": "3"
  },
  {
    "firstName": "Fernando",
    "lastName": "Alonso",
    "url": "/en/drivers/fernando-alonso.html",
    "team": "Aston Martin",
    "points": "174",
    "rank": "4"
  },
  {
    "firstName": "Carlos",
    "lastName": "Sainz",
    "url": "/en/drivers/carlos-sainz.html",
    "team": "Ferrari",
    "points": "150",
    "rank": "5"
  },
  {
    "firstName": "Charles",
    "lastName": "Leclerc",
    "url": "/en/drivers/charles-leclerc.html",
    "team": "Ferrari",
    "points": "135",
    "rank": "6"
  },
  {
    "firstName": "Lando",
    "lastName": "Norris",
    "url": "/en/drivers/lando-norris.html",
    "team": "McLaren",
    "points": "115",
    "rank": "7"
  },
  {
    "firstName": "George",
    "lastName": "Russell",
    "url": "/en/drivers/george-russell.html",
    "team": "Mercedes",
    "points": "115",
    "rank": "8"
  },
  {
    "firstName": "Oscar",
    "lastName": "Piastri",
    "url": "/en/drivers/oscar-piastri.html",
    "team": "McLaren",
    "points": "57",
    "rank": "9"
  },
  {
    "firstName": "Lance",
    "lastName": "Stroll",
    "url": "/en/drivers/lance-stroll.html",
    "team": "Aston Martin",
    "points": "47",
    "rank": "10"
  },
  {
    "firstName": "Pierre",
    "lastName": "Gasly",
    "url": "/en/drivers/pierre-gasly.html",
    "team": "Alpine",
    "points": "46",
    "rank": "11"
  },
  {
    "firstName": "Esteban",
    "lastName": "Ocon",
    "url": "/en/drivers/esteban-ocon.html",
    "team": "Alpine",
    "points": "38",
    "rank": "12"
  },
  {
    "firstName": "Alexander",
    "lastName": "Albon",
    "url": "/en/drivers/alexander-albon.html",
    "team": "Williams",
    "points": "21",
    "rank": "13"
  },
  {
    "firstName": "Nico",
    "lastName": "Hulkenberg",
    "url": "/en/drivers/nico-hulkenberg.html",
    "team": "Haas F1 Team",
    "points": "9",
    "rank": "14"
  },
  {
    "firstName": "Valtteri",
    "lastName": "Bottas",
    "url": "/en/drivers/valtteri-bottas.html",
    "team": "Alfa Romeo",
    "points": "6",
    "rank": "15"
  },
  {
    "firstName": "Guanyu",
    "lastName": "Zhou",
    "url": "/en/drivers/guanyu-zhou.html",
    "team": "Alfa Romeo",
    "points": "4",
    "rank": "16"
  },
  {
    "firstName": "Yuki",
    "lastName": "Tsunoda",
    "url": "/en/drivers/yuki-tsunoda.html",
    "team": "AlphaTauri",
    "points": "3",
    "rank": "17"
  },
  {
    "firstName": "Kevin",
    "lastName": "Magnussen",
    "url": "/en/drivers/kevin-magnussen.html",
    "team": "Haas F1 Team",
    "points": "3",
    "rank": "18"
  },
  {
    "firstName": "Liam",
    "lastName": "Lawson",
    "url": "/en/drivers/liam-lawson.html",
    "team": "AlphaTauri",
    "points": "2",
    "rank": "19"
  },
  {
    "firstName": "Logan",
    "lastName": "Sargeant",
    "url": "/en/drivers/logan-sargeant.html",
    "team": "Williams",
    "points": "0",
    "rank": "20"
  },
  {
    "firstName": "Nyck",
    "lastName": "De Vries",
    "url": "/en/drivers/nyck-de-vries.html",
    "team": "AlphaTauri",
    "points": "0",
    "rank": "21"
  },
  {
    "firstName": "Daniel",
    "lastName": "Ricciardo",
    "url": "/en/drivers/daniel-ricciardo.html",
    "team": "AlphaTauri",
    "points": "0",
    "rank": "22"
  }
]